./.gitignore
./README.md
./pyproject.toml
./.github/workflows/publish-to-pypi.yml
./inline_blocks/__init__.py
./tests/test_inline-blocks.py
pymdownx_inline_blocks-0.1.2.dist-info/METADATA
pymdownx_inline_blocks-0.1.2.dist-info/WHEEL
pymdownx_inline_blocks-0.1.2.dist-info/RECORD
